mapitio_ae/__init__.py
mapitio_ae/action_items.py
mapitio_ae/admin_site.py
mapitio_ae/apps.py
mapitio_ae/baker_recipes.py
mapitio_ae/choices.py
mapitio_ae/list_data.py
mapitio_ae/urls.py
mapitio_ae/admin/__init__.py
mapitio_ae/admin/ae_followup_admin.py
mapitio_ae/admin/ae_initial_admin.py
mapitio_ae/admin/ae_susar_admin.py
mapitio_ae/admin/ae_tmg_admin.py
mapitio_ae/admin/death_report_admin.py
mapitio_ae/admin/death_report_tmg_admin.py
mapitio_ae/admin/death_report_tmg_second_admin.py
mapitio_ae/forms/__init__.py
mapitio_ae/forms/ae_followup_form.py
mapitio_ae/forms/ae_initial_form.py
mapitio_ae/forms/ae_susar_form.py
mapitio_ae/forms/ae_tmg_form.py
mapitio_ae/forms/death_report_form.py
mapitio_ae/forms/death_report_tmg_form.py
mapitio_ae/forms/death_report_tmg_second_form.py
mapitio_ae/migrations/0001_initial.py
mapitio_ae/migrations/0002_auto_20200513_0023.py
mapitio_ae/migrations/__init__.py
mapitio_ae/models/__init__.py
mapitio_ae/models/ae_followup.py
mapitio_ae/models/ae_initial.py
mapitio_ae/models/ae_susar.py
mapitio_ae/models/ae_tmg.py
mapitio_ae/models/death_report.py
mapitio_ae/models/death_report_tmg.py
mapitio_ae/models/death_report_tmg_second.py
mapitio_ae/models/managers.py
mapitio_ae/models/model_mixins.py
mapitio_ae/pdf_reports/__init__.py
mapitio_ae/pdf_reports/ae_report.py
mapitio_ae/pdf_reports/death_report.py
mapitio_ae/pdf_reports/pdf_report_mixin.py
mapitio_ae/templates/mapitio_ae/bootstrap3/ae_initial_description.html
mapitio_ae/templatetags/__init__.py
mapitio_ae/templatetags/mapitio_ae_extras.py
mapitio_auth/__init__.py
mapitio_auth/apps.py
mapitio_auth/codenames_by_group.py
mapitio_auth/models.py
mapitio_auth/urls.py
mapitio_auth/codenames/__init__.py
mapitio_auth/codenames/auditor.py
mapitio_auth/codenames/clinic.py
mapitio_auth/codenames/export.py
mapitio_auth/codenames/pii.py
mapitio_auth/codenames/pii_view.py
mapitio_auth/codenames/screening.py
mapitio_auth/codenames/unblinding.py
mapitio_consent/__init__.py
mapitio_edc-0.1.19.dist-info/AUTHORS.rst
mapitio_edc-0.1.19.dist-info/LICENSE
mapitio_edc-0.1.19.dist-info/METADATA
mapitio_edc-0.1.19.dist-info/WHEEL
mapitio_edc-0.1.19.dist-info/top_level.txt
mapitio_edc-0.1.19.dist-info/RECORD
