Metadata-Version: 2.1
Name: mapitio-edc
Version: 0.1.19
Summary: Retrospective HIV Cohort for Diabetes Research
Home-page: https://github.com/mapitio/mapitio-edc
Author: Erik van Widenfelt
Author-email: ew2789@gmail.com
License: GPL license, see LICENSE
Keywords: django mapitio diabetes EDC
Platform: UNKNOWN
Classifier: Environment :: Web Environment
Classifier: Framework :: Django :: 3.0
Classifier: Intended Audience :: Developers
Classifier: Intended Audience :: Science/Research
Classifier: License :: OSI Approved :: GNU General Public License v3 (GPLv3)
Classifier: Operating System :: OS Independent
Classifier: Programming Language :: Python :: 3.8
Classifier: Topic :: Internet :: WWW/HTTP
Classifier: Topic :: Internet :: WWW/HTTP :: Dynamic Content
Requires-Python: >=3.7
Requires-Dist: boto3
Requires-Dist: django-environ
Requires-Dist: django-redis
Requires-Dist: django-storages
Requires-Dist: gunicorn
Requires-Dist: python-memcached
Requires-Dist: sentry-sdk
Requires-Dist: celery
Requires-Dist: django-celery-beat
Requires-Dist: django-celery-results
